Workbook
Name aporte: app!$D$16
Name patrimonio: app!$D$19
Name qtd_anos: app!$D$17
Name rendimento_carteira: app!$D$12
Name salario: app!$D$11
Name sugestao_investimento: app!$D$13
Name taxa_mensal: app!$D$18

Sheet app
B10: Configurações
B11: Salário | D11: 2000
B12: Rendimento carteira | D12: 0.006
A13: 0.3 | B13: ="Sugestão de investimento ("&A13*100&"%)" -> Sugestão de investimento (30%) | D13: =D11*A13 -> 600
B15: Investimento mensal
B16: Quanto investir por mês? | D16: 200
B17: Por quantos anos? | D17: 5
B18: Taxa de rendimento mensal? | D18: 0.01079
B19: Patrimônio acumulado? | D19: =FV(taxa_mensal,qtd_anos*12,aporte*-1) -> 16755.383
B20: Dividendos mensais? | D20: =patrimonio*rendimento_carteira -> 100.5323
B22: Cenários | C22: Patrimônio | D22: Dividendo
A23: 2 | B23: Quanto em 2 anos? | C23: =FV($D$18,$A23*12,$D$16*-1) -> 5445.5255 | D23: =C23*rendimento_carteira -> 32.673153
A24: 5 | B24: Quanto em 5 anos? | C24: =FV($D$18,$A24*12,$D$16*-1) -> 16755.383 | D24: =C24*rendimento_carteira -> 100.5323
A25: 10 | B25: Quanto em 10 anos? | C25: =FV($D$18,$A25*12,$D$16*-1) -> 48656.843 | D25: =C25*rendimento_carteira -> 291.94106
A26: 20 | B26: Quanto em 20 anos? | C26: =FV($D$18,$A26*12,$D$16*-1) -> 225039.68 | D26: =C26*rendimento_carteira -> 1350.2381
A27: 30 | B27: Quanto em 30 anos? | C27: =FV($D$18,$A27*12,$D$16*-1) -> 864433.93 | D27: =C27*rendimento_carteira -> 5186.6036
B29: Perfil | C29: Conservador
B30: Valor a ser investido por mês | C30: =aporte -> 200
B32: Tipo de FII | C32: Percentual Sugerido | D32: Valores
B33: Papel | C33: =VLOOKUP($C$29&"-"&B33,perfil_fii!$A:$D,4,FALSE) -> 0.3 | D33: =C33*$C$30 -> 60
B34: Tijolo | C34: =VLOOKUP($C$29&"-"&B34,perfil_fii!$A:$D,4,FALSE) -> 0.5 | D34: =C34*$C$30 -> 100
B35: Híbridos | C35: =VLOOKUP($C$29&"-"&B35,perfil_fii!$A:$D,4,FALSE) -> 0.1 | D35: =C35*$C$30 -> 20
B36: FOFs | C36: =VLOOKUP($C$29&"-"&B36,perfil_fii!$A:$D,4,FALSE) -> 0.1 | D36: =C36*$C$30 -> 20
B37: Desenvolvimento | C37: =VLOOKUP($C$29&"-"&B37,perfil_fii!$A:$D,4,FALSE) -> 0 | D37: =C37*$C$30 -> 0
B38: Hotelarias | C38: =VLOOKUP($C$29&"-"&B38,perfil_fii!$A:$D,4,FALSE) -> 0 | D38: =C38*$C$30 -> 0
D39: =SUM(D33:D38) -> 200

Sheet perfil_fii
A1: Chave | B1: Perfil | C1: Tipo de FII | D1: %
A2: =B2&"-"&C2 -> Conservador-Papel | B2: Conservador | C2: Papel | D2: 0.3
A3: =B3&"-"&C3 -> Conservador-Tijolo | B3: Conservador | C3: Tijolo | D3: 0.5
A4: =B4&"-"&C4 -> Conservador-Híbridos | B4: Conservador | C4: Híbridos | D4: 0.1 | G4: Moderado-Tijolo | H4: =VLOOKUP(G4,$A:$D,4,FALSE) -> 0.35
A5: =B5&"-"&C5 -> Conservador-FOFs | B5: Conservador | C5: FOFs | D5: 0.1
A6: =B6&"-"&C6 -> Conservador-Desenvolvimento | B6: Conservador | C6: Desenvolvimento | D6: 0
A7: =B7&"-"&C7 -> Conservador-Hotelarias | B7: Conservador | C7: Hotelarias | D7: 0
A8: =B8&"-"&C8 -> Moderado-Papel | B8: Moderado | C8: Papel | D8: 0.32
A9: =B9&"-"&C9 -> Moderado-Tijolo | B9: Moderado | C9: Tijolo | D9: 0.35
A10: =B10&"-"&C10 -> Moderado-Híbridos | B10: Moderado | C10: Híbridos | D10: 0.08
A11: =B11&"-"&C11 -> Moderado-FOFs | B11: Moderado | C11: FOFs | D11: 0.05
A12: =B12&"-"&C12 -> Moderado-Desenvolvimento | B12: Moderado | C12: Desenvolvimento | D12: 0.1
A13: =B13&"-"&C13 -> Moderado-Hotelarias | B13: Moderado | C13: Hotelarias | D13: 0.1
A14: =B14&"-"&C14 -> Agressivo-Papel | B14: Agressivo | C14: Papel | D14: 0.5
A15: =B15&"-"&C15 -> Agressivo-Tijolo | B15: Agressivo | C15: Tijolo | D15: 0.1
A16: =B16&"-"&C16 -> Agressivo-Híbridos | B16: Agressivo | C16: Híbridos | D16: 0.05
... A19: =B19&"-"&C19 -> Agressivo-Hotelarias | B19: Agressivo | C19: Hotelarias | D19: 0.1
